hihylang/__init__.py
hihylang/hi.hy
hihylang-1.0.dist-info/DESCRIPTION.rst
hihylang-1.0.dist-info/METADATA
hihylang-1.0.dist-info/RECORD
hihylang-1.0.dist-info/WHEEL
hihylang-1.0.dist-info/metadata.json
hihylang-1.0.dist-info/top_level.txt
