Metadata-Version: 2.0
Name: hihylang
Version: 1.0
Summary: A Hy package that says Hi.
Home-page: https://github.com/MonsieurV/hy-lang-create-package
Author: Yoan Tournade
Author-email: yoan@ytotech.com
License: MIT
Platform: any
Requires-Dist: hy
